<?xml version="1.0"?><record id="10"><meta key="0500">Fav</meta><meta key="0501">#text=txt %%rdacontent/eng</meta><meta key="0502">#unmediated=n %%rdamedia/eng</meta><meta key="0503">#volume=nc %%rdacarrier/eng</meta><meta key="1100">1590-1600 $ [late 16th century]</meta><meta key="1500">/1ned</meta><meta key="1505"> =B eng</meta><meta key="1700">/1nl</meta><meta key="3000">#Pseudo-#@Bridget"%of Sweden</meta><meta key="3121">@Birgittines of St. Mary, Double convent (Marienwater/Koudewater), Rosmalen$scr$</meta><meta key="3122">@Birgittines of St. Mary, Double convent (Marienwater/Koudewater), Rosmalen$pat$</meta><meta key="3200">@bible</meta><meta key="3200">@religious texts</meta><meta key="3250">Uden, AMR : ms. BA: 1</meta><meta key="4000">Die @passie ons liefs heeren (long version) / pseudo-Bridget of Sweden</meta><meta key="4030">Meierij van 's-Hertogenbosch (Bailiwick of 's-Hertogenbosch)</meta><meta key="4032">Rosmalen</meta><meta key="4060">174 ff</meta><meta key="4062">143x92 (c. 108x65) mm</meta><meta key="4063">12-16 lines</meta><meta key="4064">Post-medieval binding</meta><meta key="4203">This is olim ms. B:2</meta><meta key="4203">Transported in 1713 from the discontinued monastery Marienwater to Maria-Refugie in Uden</meta><meta key="4204">[inc.] Hier beghint dat liden ons lieuen heer Jhesus Christus alsoe hijt seluevr gheopenbaert heuet sijnder lieuven bruyt sinte brigita onser weerdigher moeder..</meta><meta key="4212">Sander Olsen 1977, no. 4 - Sander Olsen 1995, no. 235 - Stooker &amp; Verbeij 1997, no. 1077 - Sander Olsen 2002, p. 54</meta><meta key="4227">Probably written in the monastery Marienwater (Koudewater) in Rosmalen (f.1r: Birgitta "onser weerdigher moeder" - f.152r: S. Lambertus "patroon"). Owned by the same monastery</meta><meta key="4251">Contains binding fragment (14th/15th century?)</meta><meta key="2080">10892</meta><meta key="4701">svb</meta><meta key="4900">20-12-07 07:49:03.000</meta><meta key="6500">gospel harmony</meta><meta key="6501">mysticism</meta><meta key="7001">20-12-07 : gh</meta><meta key="7100">BA: 1</meta><meta key="7101">B:2</meta><meta key="7134">#Database BNM# =A http://www.bibliotheek.leidenuniv.nl/collecties/bijzonder/bnm.jsp</meta><meta key="7900">20-12-07 07:49:03.000</meta><meta key="7800">48054946X</meta></record>